vsixget/__init__.py
vsixget/downloader.py
vsixget-0.1.0.dist-info/licenses/LICENSE
vsixget-0.1.0.dist-info/METADATA
vsixget-0.1.0.dist-info/WHEEL
vsixget-0.1.0.dist-info/entry_points.txt
vsixget-0.1.0.dist-info/top_level.txt
vsixget-0.1.0.dist-info/RECORD
