Metadata-Version: 2.4
Name: vsixget
Version: 0.1.0
Summary: A Python tool for downloading VSIX files from the Visual Studio Marketplace
Author-email: Jeremiah K <17190268+jeremiah-k@users.noreply.github.com>
Maintainer-email: Jeremiah K <17190268+jeremiah-k@users.noreply.github.com>
License: MIT License
Project-URL: Homepage, https://github.com/jeremiah-k/vsixget
Project-URL: Repository, https://github.com/jeremiah-k/vsixget
Project-URL: Issues, https://github.com/jeremiah-k/vsixget/issues
Keywords: vscode,extensions,vsix,marketplace,download
Classifier: Development Status :: 4 - Beta
Classifier: Environment :: Console
Classifier: Intended Audience :: Developers
Classifier: License :: OSI Approved :: MIT License
Classifier: Operating System :: OS Independent
Classifier: Programming Language :: Python :: 3
Classifier: Programming Language :: Python :: 3.8
Classifier: Programming Language :: Python :: 3.9
Classifier: Programming Language :: Python :: 3.10
Classifier: Programming Language :: Python :: 3.11
Classifier: Programming Language :: Python :: 3.12
Classifier: Topic :: Software Development
Classifier: Topic :: Utilities
Requires-Python: >=3.8
License-File: LICENSE
Requires-Dist: requests>=2.25.0
Requires-Dist: packaging
Dynamic: license-file
